[{"id":"10206","title":"Elma Apartments","price":203,"currency":"EUR","country":"Portugal","departure":"AMS","departureDate":"17/04/2026","duration":4,"stars":"0","province":"Algarve","region":"Algarve","serviceType":"Logies","url":"https://referral.corendon.nl/c?c=38108&m=2315769&a=453979&r=hackerdeal2.0&u=https%3A%2F%2Fwww.corendon.nl%2Fportugal%2Falgarve%2Falbufeira%2Felma-apartments%2310206.POELM.AMSFAO.170426.3.3A1-U..","banner":"https://images.corendonresources.com/L1E10206A2W0H0.jpg?v=250618155639"},{"id":"7608","title":"Cheerfulway Choro Maris (voorheen Cheerfulway Minichoro)","price":245,"currency":"EUR","country":"Portugal","departure":"AMS","departureDate":"04/10/2026","duration":4,"stars":"3","province":"Algarve","region":"Algarve","serviceType":"Logies","url":"https://referral.corendon.nl/c?c=38108&m=2315769&a=453979&r=hackerdeal2.0&u=https%3A%2F%2Fwww.corendon.nl%2Fportugal%2Falgarve%2Falbufeira%2Fcheerfulway-choro-maris-voorheen-cheerfulway-minichoro%237608.POCMC.AMSFAO.041026.3.SZ-U..","banner":"https://images.corendonresources.com/L1E7608A2W0H0.jpg?v=241128132118"},{"id":"9907","title":"Oura Parque","price":256,"currency":"EUR","country":"Portugal","departure":"AMS","departureDate":"04/10/2026","duration":4,"stars":"3","province":"Algarve","region":"Algarve","serviceType":"Logies","url":"https://referral.corendon.nl/c?c=38108&m=2315769&a=453979&r=hackerdeal2.0&u=https%3A%2F%2Fwww.corendon.nl%2Fportugal%2Falgarve%2Falbufeira%2Foura-parque%239907.POOPQ.AMSFAO.041026.3.2A-U..","banner":"https://images.corendonresources.com/L1E9907A2W0H0.jpg?v=220522013425"},{"id":"8502","title":"Smy Santa Eulalia","price":283,"currency":"EUR","country":"Portugal","departure":"AMS","departureDate":"06/10/2026","duration":4,"stars":"3","province":"Algarve","region":"Algarve","serviceType":"Logies","url":"https://referral.corendon.nl/c?c=38108&m=2315769&a=453979&r=hackerdeal2.0&u=https%3A%2F%2Fwww.corendon.nl%2Fportugal%2Falgarve%2Falbufeira%2Fsmy-santa-eulalia%238502.POCPA.AMSFAO.061026.3.SZ-U..","banner":"https://images.corendonresources.com/L1E8502A2W0H0.jpg?v=251202110152"},{"id":"13891","title":"Carvoeiro Garden","price":287,"currency":"EUR","country":"Portugal","departure":"AMS","departureDate":"06/10/2026","duration":4,"stars":"4","province":"Algarve","region":"Algarve","serviceType":"Logies","url":"https://referral.corendon.nl/c?c=38108&m=2315769&a=453979&r=hackerdeal2.0&u=https%3A%2F%2Fwww.corendon.nl%2Fportugal%2Falgarve%2Fcarvoeiro%2Fcarvoeiro-garden%2313891.POCGA.AMSFAO.061026.3.SZ-U..","banner":"https://images.corendonresources.com/L1E13891A2W0H0.jpg?v=260129150253"},{"id":"12848","title":"Interpass Vau Hotel & Apartments","price":316,"currency":"EUR","country":"Portugal","departure":"AMS","departureDate":"06/10/2026","duration":4,"stars":"4","province":"Algarve","region":"Algarve","serviceType":"Logies en ontbijt","url":"https://referral.corendon.nl/c?c=38108&m=2315769&a=453979&r=hackerdeal2.0&u=https%3A%2F%2Fwww.corendon.nl%2Fportugal%2Falgarve%2Fpraia-da-rocha%2Finterpass-vau-hotel-apartments%2312848.POINT.AMSFAO.061026.3.DZ-F..","banner":"https://images.corendonresources.com/L1E12848A2W0H0.jpg?v=251009164104"},{"id":"13747","title":"Fly & Go Smy Santa Eulalia","price":319,"currency":"EUR","country":"Portugal","departure":"AMS","departureDate":"06/10/2026","duration":4,"stars":"3","province":"Algarve","region":"Algarve","serviceType":"Logies","url":"https://referral.corendon.nl/c?c=38108&m=2315769&a=453979&r=hackerdeal2.0&u=https%3A%2F%2Fwww.corendon.nl%2Fportugal%2Falgarve%2Falbufeira%2Ffly-go-smy-santa-eulalia%2313747.POCPAF.AMSFAO.061026.3.SZ-U..","banner":"https://images.corendonresources.com/L1E13747A2W0H0.jpg?v=251201132738"},{"id":"4912","title":"Clube Porto Mos","price":331,"currency":"EUR","country":"Portugal","departure":"AMS","departureDate":"04/10/2026","duration":4,"stars":"4","province":"Algarve","region":"Algarve","serviceType":"Logies","url":"https://referral.corendon.nl/c?c=38108&m=2315769&a=453979&r=hackerdeal2.0&u=https%3A%2F%2Fwww.corendon.nl%2Fportugal%2Falgarve%2Flagos%2Fclube-porto-mos%234912.POCPM.AMSFAO.041026.3.2A-U..","banner":"https://images.corendonresources.com/L1E4912A2W0H0.jpg?v=250910161129"},{"id":"12934","title":"Fly & Go Baia Beach Monte Gordo","price":336,"currency":"EUR","country":"Portugal","departure":"AMS","departureDate":"12/10/2026","duration":4,"stars":"4","province":"Algarve","region":"Algarve","serviceType":"Logies en ontbijt","url":"https://referral.corendon.nl/c?c=38108&m=2315769&a=453979&r=hackerdeal2.0&u=https%3A%2F%2Fwww.corendon.nl%2Fportugal%2Falgarve%2Fmonte-gordo%2Ffly-go-baia-beach-monte-gordo%2312934.POBMOF.AMSFAO.121026.3.DZ-F..","banner":"https://images.corendonresources.com/L1E12934A2W0H0.jpg?v=251121122313"},{"id":"4876","title":"Aquashow Park","price":340,"currency":"EUR","country":"Portugal","departure":"AMS","departureDate":"14/12/2026","duration":4,"stars":"4","province":"Algarve","region":"Algarve","serviceType":"Logies en ontbijt","url":"https://referral.corendon.nl/c?c=38108&m=2315769&a=453979&r=hackerdeal2.0&u=https%3A%2F%2Fwww.corendon.nl%2Fportugal%2Falgarve%2Fquarteira%2Faquashow-park%234876.POAQA.AMSFAO.141226.3.DZ-F..","banner":"https://images.corendonresources.com/L1E4876A2W0H0.jpg?v=250522142832"},{"id":"9458","title":"Vila Gale Nautico","price":341,"currency":"EUR","country":"Portugal","departure":"AMS","departureDate":"04/10/2026","duration":4,"stars":"4","province":"Algarve","region":"Algarve","serviceType":"Logies en ontbijt","url":"https://referral.corendon.nl/c?c=38108&m=2315769&a=453979&r=hackerdeal2.0&u=https%3A%2F%2Fwww.corendon.nl%2Fportugal%2Falgarve%2Farmacao-de-pera%2Fvila-gale-nautico%239458.POVNA.AMSFAO.041026.3.DZ-F..","banner":"https://images.corendonresources.com/L1E9458A2W0H0.jpg?v=251022170102"},{"id":"14072","title":"NH Lisboa Campo Grande","price":342,"currency":"EUR","country":"Portugal","departure":"EIN","departureDate":"31/08/2026","duration":3,"stars":"4","province":"Lissabon","region":"Lissabon","serviceType":"Logies en ontbijt","url":"https://referral.corendon.nl/c?c=38108&m=2315769&a=453979&r=hackerdeal2.0&u=https%3A%2F%2Fwww.corendon.nl%2Fportugal%2Flissabon%2Fnh-lisboa-campo-grande%2314072.LSNHL.EINLIS.310826.2.DZ-F..","banner":"https://images.corendonresources.com/L1E14072A7W0H0.jpg?v=260401134214"},{"id":"9445","title":"Vila Gale Cerro Alagoa","price":345,"currency":"EUR","country":"Portugal","departure":"AMS","departureDate":"04/10/2026","duration":4,"stars":"4","province":"Algarve","region":"Algarve","serviceType":"Logies en ontbijt","url":"https://referral.corendon.nl/c?c=38108&m=2315769&a=453979&r=hackerdeal2.0&u=https%3A%2F%2Fwww.corendon.nl%2Fportugal%2Falgarve%2Falbufeira%2Fvila-gale-cerro-alagoa%239445.POVGC.AMSFAO.041026.3.DZ-F..","banner":"https://images.corendonresources.com/L1E9445A2W0H0.jpg?v=251022164833"},{"id":"3619","title":"Balaia Golf Village","price":363,"currency":"EUR","country":"Portugal","departure":"AMS","departureDate":"12/10/2026","duration":4,"stars":"4","province":"Algarve","region":"Algarve","serviceType":"Logies","url":"https://referral.corendon.nl/c?c=38108&m=2315769&a=453979&r=hackerdeal2.0&u=https%3A%2F%2Fwww.corendon.nl%2Fportugal%2Falgarve%2Falbufeira%2Fbalaia-golf-village%233619.POBVI.AMSFAO.121026.3.2AS-U..","banner":"https://images.corendonresources.com/L1E3619A3W0H0.jpg?v=251020153247"},{"id":"8822","title":"Monica Isabel Beach Club","price":366,"currency":"EUR","country":"Portugal","departure":"AMS","departureDate":"12/10/2026","duration":4,"stars":"3","province":"Algarve","region":"Algarve","serviceType":"All Inclusive","url":"https://referral.corendon.nl/c?c=38108&m=2315769&a=453979&r=hackerdeal2.0&u=https%3A%2F%2Fwww.corendon.nl%2Fportugal%2Falgarve%2Falbufeira%2Fmonica-isabel-beach-club%238822.POMIB.AMSFAO.121026.3.DZ-A..","banner":"https://images.corendonresources.com/L1E8822A2W0H0.jpg?v=220522013420"},{"id":"9631","title":"Quinta Pedra Dos Bicos","price":372,"currency":"EUR","country":"Portugal","departure":"AMS","departureDate":"12/10/2026","duration":4,"stars":"4","province":"Algarve","region":"Algarve","serviceType":"Logies","url":"https://referral.corendon.nl/c?c=38108&m=2315769&a=453979&r=hackerdeal2.0&u=https%3A%2F%2Fwww.corendon.nl%2Fportugal%2Falgarve%2Falbufeira%2Fquinta-pedra-dos-bicos%239631.POPBI.AMSFAO.121026.3.2AZ-U..","banner":"https://images.corendonresources.com/L1E9631A2W0H0.jpg?v=241114124233"},{"id":"2998","title":"Auramar Beach Resort","price":401,"currency":"EUR","country":"Portugal","departure":"AMS","departureDate":"01/06/2026","duration":4,"stars":"3","province":"Algarve","region":"Algarve","serviceType":"All Inclusive","url":"https://referral.corendon.nl/c?c=38108&m=2315769&a=453979&r=hackerdeal2.0&u=https%3A%2F%2Fwww.corendon.nl%2Fportugal%2Falgarve%2Falbufeira%2Fauramar-beach-resort%232998.POABR.AMSFAO.010626.3.DZ-A..","banner":"https://images.corendonresources.com/L1E2998A2W0H0.jpg?v=251107115317"},{"id":"4180","title":"Quintinha Village","price":404,"currency":"EUR","country":"Portugal","departure":"AMS","departureDate":"30/09/2026","duration":8,"stars":"3","province":"Algarve","region":"Algarve","serviceType":"Logies","url":"https://referral.corendon.nl/c?c=38108&m=2315769&a=453979&r=hackerdeal2.0&u=https%3A%2F%2Fwww.corendon.nl%2Fportugal%2Falgarve%2Farmacao-de-pera%2Fquintinha-village%234180.POQUV.AMSFAO.300926.7.3A-U..","banner":"https://images.corendonresources.com/L1E4180A2W0H0.jpg?v=220522013529"},{"id":"13496","title":"AP Eva Senses","price":404,"currency":"EUR","country":"Portugal","departure":"AMS","departureDate":"04/10/2026","duration":4,"stars":"4","province":"Algarve","region":"Algarve","serviceType":"Logies en ontbijt","url":"https://referral.corendon.nl/c?c=38108&m=2315769&a=453979&r=hackerdeal2.0&u=https%3A%2F%2Fwww.corendon.nl%2Fportugal%2Falgarve%2Ffaro%2Fap-eva-senses%2313496.POAPE.AMSFAO.041026.3.DZL-F..","banner":"https://images.corendonresources.com/L1E13496A2W0H0.jpg?v=250911145213"},{"id":"13656","title":"Turiquintas Villas","price":410,"currency":"EUR","country":"Portugal","departure":"AMS","departureDate":"04/10/2026","duration":4,"stars":"3","province":"Algarve","region":"Algarve","serviceType":"Logies","url":"https://referral.corendon.nl/c?c=38108&m=2315769&a=453979&r=hackerdeal2.0&u=https%3A%2F%2Fwww.corendon.nl%2Fportugal%2Falgarve%2Farmacao-de-pera%2Fturiquintas-villas%2313656.POTUV.AMSFAO.041026.3.3VS-U..","banner":"https://images.corendonresources.com/L1E13656A2W0H0.jpg?v=251121120214"},{"id":"7577","title":"Aqua Pedra Dos Bicos","price":414,"currency":"EUR","country":"Portugal","departure":"AMS","departureDate":"12/10/2026","duration":4,"stars":"4","province":"Algarve","region":"Algarve","serviceType":"Logies en ontbijt","url":"https://referral.corendon.nl/c?c=38108&m=2315769&a=453979&r=hackerdeal2.0&u=https%3A%2F%2Fwww.corendon.nl%2Fportugal%2Falgarve%2Falbufeira%2Faqua-pedra-dos-bicos%237577.POPED.AMSFAO.121026.3.DS-F..","banner":"https://images.corendonresources.com/L1E7577A2W0H0.jpg?v=251112181647"},{"id":"13378","title":"Fly & Go Quintinha Village","price":483,"currency":"EUR","country":"Portugal","departure":"AMS","departureDate":"05/10/2026","duration":8,"stars":"3","province":"Algarve","region":"Algarve","serviceType":"Logies","url":"https://referral.corendon.nl/c?c=38108&m=2315769&a=453979&r=hackerdeal2.0&u=https%3A%2F%2Fwww.corendon.nl%2Fportugal%2Falgarve%2Farmacao-de-pera%2Fa%2Ffly-go-quintinha-village%2313378.POQUVF.AMSFAO.051026.7.3A-U..","banner":"https://images.corendonresources.com/L1E13378A2W0H0.jpg?v=250724081451"},{"id":"11495","title":"Fly & Go Ukino Terrace","price":487,"currency":"EUR","country":"Portugal","departure":"AMS","departureDate":"14/10/2026","duration":8,"stars":"3","province":"Algarve","region":"Algarve","serviceType":"Logies","url":"https://referral.corendon.nl/c?c=38108&m=2315769&a=453979&r=hackerdeal2.0&u=https%3A%2F%2Fwww.corendon.nl%2Fportugal%2Falgarve%2Farmacao-de-pera%2Ffly-go-ukino-terrace%2311495.POBSTF.AMSFAO.141026.7.2A1-U..","banner":"https://images.corendonresources.com/L1E11495A2W0H0.jpg?v=230915164835"},{"id":"14051","title":"Iberostar Selection Lisboa","price":489,"currency":"EUR","country":"Portugal","departure":"EIN","departureDate":"30/08/2026","duration":4,"stars":"5","province":"Lissabon","region":"Lissabon","serviceType":"Logies","url":"https://referral.corendon.nl/c?c=38108&m=2315769&a=453979&r=hackerdeal2.0&u=https%3A%2F%2Fwww.corendon.nl%2Fportugal%2Flissabon%2Fiberostar-selection-lisboa%2314051.LSISL.EINLIS.300826.3.DS-U..","banner":"https://images.corendonresources.com/L1E14051A2W0H0.jpg?v=260325104938"},{"id":"9454","title":"AP Adriana Beach Resort","price":499,"currency":"EUR","country":"Portugal","departure":"AMS","departureDate":"12/10/2026","duration":4,"stars":"4","province":"Algarve","region":"Algarve","serviceType":"All Inclusive","url":"https://referral.corendon.nl/c?c=38108&m=2315769&a=453979&r=hackerdeal2.0&u=https%3A%2F%2Fwww.corendon.nl%2Fportugal%2Falgarve%2Falbufeira%2Fap-adriana-beach-resort%239454.POADR.AMSFAO.121026.3.DZ2-A..","banner":"https://images.corendonresources.com/L1E9454A2W0H0.jpg?v=250226095844"},{"id":"12930","title":"Dorisol Estrelicia Hotel","price":507,"currency":"EUR","country":"Portugal","departure":"AMS","departureDate":"27/06/2026","duration":6,"stars":"3","province":"Madeira","region":"Madeira","serviceType":"Logies en ontbijt","url":"https://referral.corendon.nl/c?c=38108&m=2315769&a=453979&r=hackerdeal2.0&u=https%3A%2F%2Fwww.corendon.nl%2Fportugal%2Fmadeira%2Ffunchal%2Fdorisol-estrelicia-hotel%2312930.FNDES.AMSFNC.270626.5.DZ-F..","banner":"https://images.corendonresources.com/L1E12930A2W0H0.jpg?v=241017084854"},{"id":"7795","title":"Dorisol Mimosa","price":510,"currency":"EUR","country":"Portugal","departure":"AMS","departureDate":"20/06/2026","duration":6,"stars":"3","province":"Madeira","region":"Madeira","serviceType":"Logies","url":"https://referral.corendon.nl/c?c=38108&m=2315769&a=453979&r=hackerdeal2.0&u=https%3A%2F%2Fwww.corendon.nl%2Fportugal%2Fmadeira%2Ffunchal%2Fdorisol-mimosa%237795.FNMIM.AMSFNC.200626.5.S1-U..","banner":"https://images.corendonresources.com/L1E7795A2W0H0.jpg?v=251017150334"},{"id":"7799","title":"Dorisol Buganvilia","price":517,"currency":"EUR","country":"Portugal","departure":"AMS","departureDate":"14/10/2026","duration":6,"stars":"3","province":"Madeira","region":"Madeira","serviceType":"Logies","url":"https://referral.corendon.nl/c?c=38108&m=2315769&a=453979&r=hackerdeal2.0&u=https%3A%2F%2Fwww.corendon.nl%2Fportugal%2Fmadeira%2Ffunchal%2Fdorisol-buganvilia%237799.FNBUG.AMSFNC.141026.5.S1-U..","banner":"https://images.corendonresources.com/L1E7799A2W0H0.jpg?v=240703165333"},{"id":"6457","title":"Belver Boa Vista Hotel & Spa","price":526,"currency":"EUR","country":"Portugal","departure":"AMS","departureDate":"08/04/2026","duration":8,"stars":"4","province":"Algarve","region":"Algarve","serviceType":"Logies","url":"https://referral.corendon.nl/c?c=38108&m=2315769&a=453979&r=hackerdeal2.0&u=https%3A%2F%2Fwww.corendon.nl%2Fportugal%2Falgarve%2Falbufeira%2Fbelver-boa-vista-hotel-spa%236457.POBEB.AMSFAO.080426.7.DZ-U..","banner":"https://images.corendonresources.com/L1E6457A2W0H0.jpg?v=250513092046"},{"id":"3582","title":"Albufeira Sol","price":536,"currency":"EUR","country":"Portugal","departure":"AMS","departureDate":"03/10/2026","duration":5,"stars":"4","province":"Algarve","region":"Algarve","serviceType":"All Inclusive","url":"https://referral.corendon.nl/c?c=38108&m=2315769&a=453979&r=hackerdeal2.0&u=https%3A%2F%2Fwww.corendon.nl%2Fportugal%2Falgarve%2Falbufeira%2Falbufeira-sol%233582.POALF.AMSFAO.031026.4.S1-A..","banner":"https://images.corendonresources.com/L1E3582A2W0H0.jpg?v=240130104124"},{"id":"12322","title":"Pestana Blue Alvor Beach","price":555,"currency":"EUR","country":"Portugal","departure":"AMS","departureDate":"12/10/2026","duration":4,"stars":"5","province":"Algarve","region":"Algarve","serviceType":"All Inclusive","url":"https://referral.corendon.nl/c?c=38108&m=2315769&a=453979&r=hackerdeal2.0&u=https%3A%2F%2Fwww.corendon.nl%2Fportugal%2Falgarve%2Falvor%2Fpestana-blue-alvor-beach%2312322.POPEA.AMSFAO.121026.3.DZM-A..","banner":"https://images.corendonresources.com/L1E12322A2W0H0.jpg?v=251009164240"},{"id":"8211","title":"Terrace Mar","price":580,"currency":"EUR","country":"Portugal","departure":"AMS","departureDate":"30/06/2026","duration":6,"stars":"4","province":"Madeira","region":"Madeira","serviceType":"Logies","url":"https://referral.corendon.nl/c?c=38108&m=2315769&a=453979&r=hackerdeal2.0&u=https%3A%2F%2Fwww.corendon.nl%2Fportugal%2Fmadeira%2Ffunchal%2Fterrace-mar%238211.FNTER.AMSFNC.300626.5.JZ-U..","banner":"https://images.corendonresources.com/L1E8211A2W0H0.jpg?v=220522081117"},{"id":"8005","title":"Dom Pedro Garajau","price":587,"currency":"EUR","country":"Portugal","departure":"AMS","departureDate":"25/06/2026","duration":6,"stars":"3","province":"Madeira","region":"Madeira","serviceType":"Logies en ontbijt","url":"https://referral.corendon.nl/c?c=38108&m=2315769&a=453979&r=hackerdeal2.0&u=https%3A%2F%2Fwww.corendon.nl%2Fportugal%2Fmadeira%2Fcanico%2Fdom-pedro-garajau%238005.FNDPG.AMSFNC.250626.5.DZM-F..","banner":"https://images.corendonresources.com/L1E8005A2W0H0.jpg?v=220927092923"},{"id":"7789","title":"Duas Torres","price":603,"currency":"EUR","country":"Portugal","departure":"AMS","departureDate":"27/06/2026","duration":6,"stars":"4","province":"Madeira","region":"Madeira","serviceType":"Logies","url":"https://referral.corendon.nl/c?c=38108&m=2315769&a=453979&r=hackerdeal2.0&u=https%3A%2F%2Fwww.corendon.nl%2Fportugal%2Fmadeira%2Ffunchal%2Fduas-torres%237789.FNDUA.AMSFNC.270626.5.SZI-U..","banner":"https://images.corendonresources.com/L1E7789A2W0H0.jpg?v=220522080827"},{"id":"13376","title":"Fly & Go Ancora Park","price":603,"currency":"EUR","country":"Portugal","departure":"AMS","departureDate":"05/10/2026","duration":8,"stars":"4","province":"Algarve","region":"Algarve","serviceType":"Logies","url":"https://referral.corendon.nl/c?c=38108&m=2315769&a=453979&r=hackerdeal2.0&u=https%3A%2F%2Fwww.corendon.nl%2Fportugal%2Falgarve%2Flagos%2Ffly-go-ancora-park%2313376.POACPF.AMSFAO.051026.7.DZP-U..","banner":"https://images.corendonresources.com/L1E13376A2W0H0.jpg?v=250724074605"},{"id":"13551","title":"Fly & Go Dom Pedro Lagos","price":611,"currency":"EUR","country":"Portugal","departure":"AMS","departureDate":"14/10/2026","duration":8,"stars":"3","province":"Algarve","region":"Algarve","serviceType":"Logies","url":"https://referral.corendon.nl/c?c=38108&m=2315769&a=453979&r=hackerdeal2.0&u=https%3A%2F%2Fwww.corendon.nl%2Fportugal%2Falgarve%2Flagos%2Ffly-go-dom-pedro-lagos%2313551.PODOMF.AMSFAO.141026.7.SZL-U..","banner":"https://images.corendonresources.com/L1E13551A2W0H0.jpg?v=251014080621"},{"id":"12739","title":"Fly & Go Regency Salgados","price":623,"currency":"EUR","country":"Portugal","departure":"RTM","departureDate":"04/05/2026","duration":8,"stars":"4","province":"Algarve","region":"Algarve","serviceType":"Logies en ontbijt","url":"https://referral.corendon.nl/c?c=38108&m=2315769&a=453979&r=hackerdeal2.0&u=https%3A%2F%2Fwww.corendon.nl%2Fportugal%2Falgarve%2Fgale%2Ffly-go-regency-salgados%2312739.PORSAF.RTMFAO.040526.7.DE-F..","banner":"https://images.corendonresources.com/L1E12739A2W0H0.jpg?v=240808093008"},{"id":"7793","title":"Dom Pedro Madeira","price":641,"currency":"EUR","country":"Portugal","departure":"AMS","departureDate":"14/10/2026","duration":6,"stars":"4","province":"Madeira","region":"Madeira","serviceType":"Logies en ontbijt","url":"https://referral.corendon.nl/c?c=38108&m=2315769&a=453979&r=hackerdeal2.0&u=https%3A%2F%2Fwww.corendon.nl%2Fportugal%2Fmadeira%2Fmachico%2Fdom-pedro-madeira%237793.FNDPB.AMSFNC.141026.5.DZ1-F..","banner":"https://images.corendonresources.com/L1E7793A2W0H0.jpg?v=220927093104"},{"id":"8024","title":"Dom Jose Beach Hotel","price":644,"currency":"EUR","country":"Portugal","departure":"AMS","departureDate":"08/04/2026","duration":8,"stars":"3","province":"Algarve","region":"Algarve","serviceType":"Logies en ontbijt","url":"https://referral.corendon.nl/c?c=38108&m=2315769&a=453979&r=hackerdeal2.0&u=https%3A%2F%2Fwww.corendon.nl%2Fportugal%2Falgarve%2Fquarteira%2Fdom-jose-beach-hotel%238024.PODOJ.AMSFAO.080426.7.DZ-F..","banner":"https://images.corendonresources.com/L1E8024A2W0H0.jpg?v=220522015424"},{"id":"13786","title":"Fly & Go Pelican Alvor","price":646,"currency":"EUR","country":"Portugal","departure":"AMS","departureDate":"14/10/2026","duration":8,"stars":"4","province":"Algarve","region":"Algarve","serviceType":"Logies","url":"https://referral.corendon.nl/c?c=38108&m=2315769&a=453979&r=hackerdeal2.0&u=https%3A%2F%2Fwww.corendon.nl%2Fportugal%2Falgarve%2Falvor%2Ffly-go-pelican-alvor%2313786.POPELF.AMSFAO.141026.7.SZL-U..","banner":"https://images.corendonresources.com/L1E13786A2W0H0.jpg?v=251209084049"}]